serialtools/__init__.py
serialtools/__main__.py
serialtools/bus.py
serialtools/database.py
serialtools/database_config.py
serialtools/py.typed
serialtools/apps/__init__.py
serialtools/apps/decode.py
serialtools/apps/dump.py
serialtools/apps/rawsplit.py
serialtools/apps/send.py
serialtools-0.9.1.dist-info/entry_points.txt
serialtools-0.9.1.dist-info/LICENSE
serialtools-0.9.1.dist-info/WHEEL
serialtools-0.9.1.dist-info/METADATA
serialtools-0.9.1.dist-info/RECORD
