Metadata-Version: 2.1
Name: serialtools
Version: 0.9.1
Summary: Tools to work with a serial bus
Author-email: erzo <erzo@posteo.de>
Requires-Python: >=3.6
Classifier: Operating System :: POSIX
Classifier: Operating System :: Unix
Classifier: Environment :: Console
Classifier: License :: OSI Approved :: BSD License
Requires-Dist: pyserial
Requires-Dist: confattr >= 1.2.1
Requires-Dist: bitstruct
Project-URL: Bug tracker, https://gitlab.com/erzo/serialtools/-/issues
Project-URL: Change log, https://gitlab.com/erzo/serialtools/-/tags
Project-URL: Documentation, https://erzo.gitlab.io/serialtools/latest
Project-URL: Source code, https://gitlab.com/erzo/serialtools
